pyfileindex/__init__.py
pyfileindex/_version.py
pyfileindex/pyfileindex.py
pyfileindex-0.1.3.dist-info/METADATA
pyfileindex-0.1.3.dist-info/WHEEL
pyfileindex-0.1.3.dist-info/licenses/LICENSE
pyfileindex-0.1.3.dist-info/RECORD
