Metadata-Version: 2.4
Name: pyfileindex
Version: 0.1.3
Summary: pyfileindex - pythonic file system index
Project-URL: Homepage, https://github.com/pyiron/pyfileindex
Project-URL: Documentation, https://github.com/pyiron/pyfileindex
Project-URL: Repository, https://github.com/pyiron/pyfileindex
Author-email: Jan Janssen <janssen@mpie.de>
License: BSD 3-Clause License
License-File: LICENSE
Keywords: pyiron
Classifier: Development Status :: 5 - Production/Stable
Classifier: Intended Audience :: Science/Research
Classifier: License :: OSI Approved :: BSD License
Classifier: Operating System :: OS Independent
Classifier: Programming Language :: Python :: 3.9
Classifier: Programming Language :: Python :: 3.10
Classifier: Programming Language :: Python :: 3.11
Classifier: Programming Language :: Python :: 3.12
Classifier: Programming Language :: Python :: 3.13
Classifier: Programming Language :: Python :: 3.14
Classifier: Topic :: Scientific/Engineering :: Physics
Requires-Python: <3.15,>=3.9
Requires-Dist: pandas<=3.0.0,>=1.5.3
